<?xml version="1.0" encoding="UTF-8" standalone="no"?>
<UserData>
    <User username="supra">
        <count>1</count>
        <Portfolio1>
            <ticker1>MSFT</ticker1>
            <qty1>10</qty1>
            <PurchaseDate1>2022-12-12</PurchaseDate1>
            <ticker1>AAPL</ticker1>
            <qty1>200.0420723128869</qty1>
            <PurchaseDate1>2015-10-10</PurchaseDate1>
            <ticker1>TSLA</ticker1>
            <qty1>150</qty1>
            <PurchaseDate1>2020-10-10</PurchaseDate1>
            <ticker1>MSFT</ticker1>
            <qty1>105.8747494091761</qty1>
            <PurchaseDate1>2022-12-12</PurchaseDate1>
            <ticker1>TSLA</ticker1>
            <qty1>13.63997765987155</qty1>
            <PurchaseDate1>2022-12-12</PurchaseDate1>
        </Portfolio1>
    </User>
</UserData>
